autodistill_fastsam/__init__.py
autodistill_fastsam/helpers.py
autodistill_fastsam/model.py
autodistill_fastsam-0.1.1.dist-info/LICENSE
autodistill_fastsam-0.1.1.dist-info/METADATA
autodistill_fastsam-0.1.1.dist-info/WHEEL
autodistill_fastsam-0.1.1.dist-info/top_level.txt
autodistill_fastsam-0.1.1.dist-info/RECORD
